[{"container.id":"3664da43153e5051d2c104b66787eed90be022efd5f3d45eec9b9a4e47b4c718","os.description":"Linux 5.15.153.1-microsoft-standard-WSL2","process.command_line":"/opt/java/openjdk/bin/java -javaagent:/usr/src/app/opentelemetry-javaagent.jar oteldemo.AdService","service.name":"adservice","telemetry.sdk.language":"java","logRecords_severityText":"WARN","logRecords_body_stringValue":"GetAds Failed with status Status{code=UNAVAILABLE, description=null, cause=null}","traceId":"ed8b4191838daec751003df550476f1d","observedTimeUnixNano":"2024-08-21 22:45:58"},{"container.id":"3664da43153e5051d2c104b66787eed90be022efd5f3d45eec9b9a4e47b4c718","os.description":"Linux 5.15.153.1-microsoft-standard-WSL2","process.command_line":"/opt/java/openjdk/bin/java -javaagent:/usr/src/app/opentelemetry-javaagent.jar oteldemo.AdService","service.name":"adservice","telemetry.sdk.language":"java","logRecords_severityText":"WARN","logRecords_body_stringValue":"GetAds Failed with status Status{code=UNAVAILABLE, description=null, cause=null}","traceId":"8158abd05277a500eb4e995fedf276ea","observedTimeUnixNano":"2024-08-21 22:46:10"},{"container.id":"3664da43153e5051d2c104b66787eed90be022efd5f3d45eec9b9a4e47b4c718","os.description":"Linux 5.15.153.1-microsoft-standard-WSL2","process.command_line":"/opt/java/openjdk/bin/java -javaagent:/usr/src/app/opentelemetry-javaagent.jar oteldemo.AdService","service.name":"adservice","telemetry.sdk.language":"java","logRecords_severityText":"WARN","logRecords_body_stringValue":"GetAds Failed with status Status{code=UNAVAILABLE, description=null, cause=null}","traceId":"0b001f6ed9b5f43933748670d377ade9","observedTimeUnixNano":"2024-08-21 22:46:22"},{"container.id":"3664da43153e5051d2c104b66787eed90be022efd5f3d45eec9b9a4e47b4c718","os.description":"Linux 5.15.153.1-microsoft-standard-WSL2","process.command_line":"/opt/java/openjdk/bin/java -javaagent:/usr/src/app/opentelemetry-javaagent.jar oteldemo.AdService","service.name":"adservice","telemetry.sdk.language":"java","logRecords_severityText":"WARN","logRecords_body_stringValue":"GetAds Failed with status Status{code=UNAVAILABLE, description=null, cause=null}","traceId":"10eea5e259ca7ea2733956ce9b0ca391","observedTimeUnixNano":"2024-08-21 22:46:41"},{"container.id":"3664da43153e5051d2c104b66787eed90be022efd5f3d45eec9b9a4e47b4c718","os.description":"Linux 5.15.153.1-microsoft-standard-WSL2","process.command_line":"/opt/java/openjdk/bin/java -javaagent:/usr/src/app/opentelemetry-javaagent.jar oteldemo.AdService","service.name":"adservice","telemetry.sdk.language":"java","logRecords_severityText":"WARN","logRecords_body_stringValue":"GetAds Failed with status Status{code=UNAVAILABLE, description=null, cause=null}","traceId":"d2f14f9b665e00fbb35c2ad96650791e","observedTimeUnixNano":"2024-08-21 22:47:31"},{"container.id":"3664da43153e5051d2c104b66787eed90be022efd5f3d45eec9b9a4e47b4c718","os.description":"Linux 5.15.153.1-microsoft-standard-WSL2","process.command_line":"/opt/java/openjdk/bin/java -javaagent:/usr/src/app/opentelemetry-javaagent.jar oteldemo.AdService","service.name":"adservice","telemetry.sdk.language":"java","logRecords_severityText":"WARN","logRecords_body_stringValue":"GetAds Failed with status Status{code=UNAVAILABLE, description=null, cause=null}","traceId":"a3068c5690d7e955872ea04eb2f2859b","observedTimeUnixNano":"2024-08-21 22:47:46"}]