{"resourceSpans":[{"resource":{"attributes":[{"key":"docker.cli.cobra.command_path","value":{"stringValue":"docker compose"}},{"key":"host.name","value":{"stringValue":"3bf7f54b750d"}},{"key":"os.description","value":{"stringValue":"Debian GNU/Linux Debian GNU/Linux 12 (bookworm) (Linux 3bf7f54b750d 5.15.153.1-microsoft-standard-WSL2 #1 SMP Fri Mar 29 23:14:13 UTC 2024 x86_64)"}},{"key":"os.type","value":{"stringValue":"linux"}},{"key":"process.runtime.version","value":{"stringValue":"go1.22.5"}},{"key":"service.name","value":{"stringValue":"flagd"}},{"key":"service.version","value":{"stringValue":"v0.11.1"}},{"key":"telemetry.sdk.language","value":{"stringValue":"go"}},{"key":"telemetry.sdk.name","value":{"stringValue":"opentelemetry"}},{"key":"telemetry.sdk.version","value":{"stringValue":"1.28.0"}}]},"scopeSpans":[{"scope":{"name":"jsonEvaluator"},"spans":[{"traceId":"09c020478f179cd2e366e0d8cb227fa1","spanId":"9534ec56c04805d4","parentSpanId":"","flags":256,"name":"flagSync","kind":1,"startTimeUnixNano":"1724247931602997166","endTimeUnixNano":"1724247931606143990","attributes":[{"key":"feature_flag.source","value":{"stringValue":"./etc/flagd/demo.flagd.json"}},{"key":"feature_flag.sync_type","value":{"stringValue":"ALL"}},{"key":"feature_flag.change_count","value":{"intValue":"11"}}],"status":{}}]}],"schemaUrl":"https://opentelemetry.io/schemas/1.26.0"}]}
{"resourceSpans":[{"resource":{"attributes":[{"key":"service.name","value":{"stringValue":"paymentservice"}},{"key":"telemetry.sdk.language","value":{"stringValue":"nodejs"}},{"key":"telemetry.sdk.name","value":{"stringValue":"opentelemetry"}},{"key":"telemetry.sdk.version","value":{"stringValue":"1.24.1"}},{"key":"container.id","value":{"stringValue":"d606a76c1a13669be761135d64f0a1acc9a58322bbd3d212397b1265e3864db5"}},{"key":"docker.cli.cobra.command_path","value":{"stringValue":"docker compose"}},{"key":"host.name","value":{"stringValue":"d606a76c1a13"}},{"key":"host.arch","value":{"stringValue":"amd64"}},{"key":"os.type","value":{"stringValue":"linux"}},{"key":"os.version","value":{"stringValue":"5.15.153.1-microsoft-standard-WSL2"}},{"key":"process.pid","value":{"intValue":"18"}},{"key":"process.executable.name","value":{"stringValue":"node"}},{"key":"process.executable.path","value":{"stringValue":"/usr/local/bin/node"}},{"key":"process.command_args","value":{"arrayValue":{"values":[{"stringValue":"/usr/local/bin/node"},{"stringValue":"--require"},{"stringValue":"./opentelemetry.js"},{"stringValue":"/usr/src/app/index.js"}]}}},{"key":"process.runtime.version","value":{"stringValue":"21.7.3"}},{"key":"process.runtime.name","value":{"stringValue":"nodejs"}},{"key":"process.runtime.description","value":{"stringValue":"Node.js"}},{"key":"process.command","value":{"stringValue":"/usr/src/app/index.js"}},{"key":"process.owner","value":{"stringValue":"node"}}]},"scopeSpans":[{"scope":{"name":"@opentelemetry/instrumentation-dns","version":"0.36.1"},"spans":[{"traceId":"d6285a5455052744ddca1abd82f1c414","spanId":"dd1044de215e7423","parentSpanId":"","name":"dns.lookup","kind":3,"startTimeUnixNano":"1724247935530000000","endTimeUnixNano":"1724247935530387475","attributes":[{"key":"peer.ipv4","value":{"stringValue":"0.0.0.0"}}],"status":{}},{"traceId":"057984531f73b7c6dc22618c442b510e","spanId":"5fb9dbd6edd8bb8f","parentSpanId":"d5c2d3aff9324d3c","name":"dns.lookup","kind":3,"startTimeUnixNano":"1724247935522000000","endTimeUnixNano":"1724247935538942206","attributes":[{"key":"dns.error_message","value":{"stringValue":"getaddrinfo ENOTFOUND metadata.google.internal."}},{"key":"dns.error_name","value":{"stringValue":"Error"}}],"status":{"message":"getaddrinfo ENOTFOUND metadata.google.internal.","code":2}}]},{"scope":{"name":"@opentelemetry/instrumentation-net","version":"0.36.0"},"spans":[{"traceId":"057984531f73b7c6dc22618c442b510e","spanId":"c128cab2758713e1","parentSpanId":"d5c2d3aff9324d3c","name":"tcp.connect","kind":1,"startTimeUnixNano":"1724247935519000000","endTimeUnixNano":"1724247935539440341","attributes":[{"key":"net.transport","value":{"stringValue":"ip_tcp"}},{"key":"net.peer.name","value":{"stringValue":"metadata.google.internal."}},{"key":"net.peer.port","value":{"intValue":"80"}}],"status":{"message":"getaddrinfo ENOTFOUND metadata.google.internal.","code":2}},{"traceId":"a6675519982455cee02addbcafbff9af","spanId":"b0d04ffeb2c4435b","parentSpanId":"f3c643c4d944b835","name":"tcp.connect","kind":1,"startTimeUnixNano":"1724247935514000000","endTimeUnixNano":"1724247935552227586","attributes":[{"key":"net.transport","value":{"stringValue":"ip_tcp"}},{"key":"net.peer.name","value":{"stringValue":"169.254.169.254"}},{"key":"net.peer.port","value":{"intValue":"80"}}],"status":{"message":"connect ECONNREFUSED 169.254.169.254:80","code":2}}]},{"scope":{"name":"@opentelemetry/instrumentation-http","version":"0.51.1"},"spans":[{"traceId":"057984531f73b7c6dc22618c442b510e","spanId":"d5c2d3aff9324d3c","parentSpanId":"","name":"GET","kind":3,"startTimeUnixNano":"1724247935517000000","endTimeUnixNano":"1724247935540643805","attributes":[{"key":"http.url","value":{"stringValue":"http://metadata.google.internal./computeMetadata/v1/instance"}},{"key":"http.method","value":{"stringValue":"GET"}},{"key":"http.target","value":{"stringValue":"/computeMetadata/v1/instance"}},{"key":"net.peer.name","value":{"stringValue":"metadata.google.internal."}},{"key":"http.host","value":{"stringValue":"metadata.google.internal.:80"}},{"key":"http.error_name","value":{"stringValue":"Error"}},{"key":"http.error_message","value":{"stringValue":"getaddrinfo ENOTFOUND metadata.google.internal."}}],"events":[{"timeUnixNano":"1724247935540580212","name":"exception","attributes":[{"key":"exception.type","value":{"stringValue":"ENOTFOUND"}},{"key":"exception.message","value":{"stringValue":"getaddrinfo ENOTFOUND metadata.google.internal."}},{"key":"exception.stacktrace","value":{"stringValue":"Error: getaddrinfo ENOTFOUND metadata.google.internal.\n    at GetAddrInfoReqWrap.onlookupall [as oncomplete] (node:dns:118:26)\n    at GetAddrInfoReqWrap.callbackTrampoline (node:internal/async_hooks:130:17)"}}]}],"status":{"message":"getaddrinfo ENOTFOUND metadata.google.internal.","code":2}},{"traceId":"a6675519982455cee02addbcafbff9af","spanId":"f3c643c4d944b835","parentSpanId":"","name":"GET","kind":3,"startTimeUnixNano":"1724247935510000000","endTimeUnixNano":"1724247935552642935","attributes":[{"key":"http.url","value":{"stringValue":"http://169.254.169.254/computeMetadata/v1/instance"}},{"key":"http.method","value":{"stringValue":"GET"}},{"key":"http.target","value":{"stringValue":"/computeMetadata/v1/instance"}},{"key":"net.peer.name","value":{"stringValue":"169.254.169.254"}},{"key":"http.host","value":{"stringValue":"169.254.169.254:80"}},{"key":"http.error_name","value":{"stringValue":"Error"}},{"key":"http.error_message","value":{"stringValue":"connect ECONNREFUSED 169.254.169.254:80"}}],"events":[{"timeUnixNano":"1724247935552605464","name":"exception","attributes":[{"key":"exception.type","value":{"stringValue":"ECONNREFUSED"}},{"key":"exception.message","value":{"stringValue":"connect ECONNREFUSED 169.254.169.254:80"}},{"key":"exception.stacktrace","value":{"stringValue":"Error: connect ECONNREFUSED 169.254.169.254:80\n    at TCPConnectWrap.afterConnect [as oncomplete] (node:net:1605:16)\n    at TCPConnectWrap.callbackTrampoline (node:internal/async_hooks:130:17)"}}]}],"status":{"message":"connect ECONNREFUSED 169.254.169.254:80","code":2}}]}]}]}
{"resourceSpans":[{"resource":{"attributes":[{"key":"docker.cli.cobra.command_path","value":{"stringValue":"docker%20compose"}},{"key":"service.name","value":{"stringValue":"frontend-proxy"}}]},"scopeSpans":[{"scope":{},"spans":[{"traceId":"ae93a08ae07df3975d4d49129b41f1f5","spanId":"62e971d082ac916e","parentSpanId":"b094eff5f151ed74","name":"router frontend egress","kind":3,"startTimeUnixNano":"1724247951836235000","endTimeUnixNano":"1724247952014835000","attributes":[{"key":"http.protocol","value":{"stringValue":"HTTP/1.1"}},{"key":"upstream_address","value":{"stringValue":"172.18.0.23:8080"}},{"key":"peer.address","value":{"stringValue":"172.18.0.23:8080"}},{"key":"component","value":{"stringValue":"proxy"}},{"key":"upstream_cluster","value":{"stringValue":"frontend"}},{"key":"upstream_cluster.name","value":{"stringValue":"frontend"}},{"key":"http.status_code","value":{"stringValue":"200"}},{"key":"response_flags","value":{"stringValue":"-"}}],"status":{}},{"traceId":"ae93a08ae07df3975d4d49129b41f1f5","spanId":"b094eff5f151ed74","parentSpanId":"","name":"ingress","kind":2,"startTimeUnixNano":"1724247951835993000","endTimeUnixNano":"1724247952014887000","attributes":[{"key":"node_id","value":{"stringValue":""}},{"key":"zone","value":{"stringValue":""}},{"key":"guid:x-request-id","value":{"stringValue":"d0058dd6-e130-9997-a327-50219f0b35ff"}},{"key":"http.url","value":{"stringValue":"http://frontend-proxy:8080/cart"}},{"key":"http.method","value":{"stringValue":"GET"}},{"key":"downstream_cluster","value":{"stringValue":"-"}},{"key":"user_agent","value":{"stringValue":"Mozilla/5.0 (X11; Linux x86_64) AppleWebKit/537.36 (KHTML, like Gecko) HeadlessChrome/120.0.6099.28 Safari/537.36"}},{"key":"http.protocol","value":{"stringValue":"HTTP/1.1"}},{"key":"peer.address","value":{"stringValue":"172.18.0.24"}},{"key":"request_size","value":{"stringValue":"0"}},{"key":"response_size","value":{"stringValue":"5742"}},{"key":"component","value":{"stringValue":"proxy"}},{"key":"upstream_cluster","value":{"stringValue":"frontend"}},{"key":"upstream_cluster.name","value":{"stringValue":"frontend"}},{"key":"http.status_code","value":{"stringValue":"200"}},{"key":"response_flags","value":{"stringValue":"-"}}],"status":{}},{"traceId":"ccf4114a135139c047b9846dc936d87a","spanId":"4707320467da397d","parentSpanId":"2033f34e7968b4ce","name":"router frontend egress","kind":3,"startTimeUnixNano":"1724247952029110000","endTimeUnixNano":"1724247952098152000","attributes":[{"key":"http.protocol","value":{"stringValue":"HTTP/1.1"}},{"key":"upstream_address","value":{"stringValue":"172.18.0.23:8080"}},{"key":"peer.address","value":{"stringValue":"172.18.0.23:8080"}},{"key":"component","value":{"stringValue":"proxy"}},{"key":"upstream_cluster","value":{"stringValue":"frontend"}},{"key":"upstream_cluster.name","value":{"stringValue":"frontend"}},{"key":"http.status_code","value":{"stringValue":"200"}},{"key":"response_flags","value":{"stringValue":"-"}}],"status":{}},{"traceId":"ccf4114a135139c047b9846dc936d87a","spanId":"2033f34e7968b4ce","parentSpanId":"","name":"ingress","kind":2,"startTimeUnixNano":"1724247952028917000","endTimeUnixNano":"1724247952098173000","attributes":[{"key":"node_id","value":{"stringValue":""}},{"key":"zone","value":{"stringValue":""}},{"key":"guid:x-request-id","value":{"stringValue":"c8385122-b2c8-9f84-9c54-c7f015bb42fc"}},{"key":"http.url","value":{"stringValue":"http://frontend-proxy:8080/_next/static/css/885c0a76d639b07f.css"}},{"key":"http.method","value":{"stringValue":"GET"}},{"key":"downstream_cluster","value":{"stringValue":"-"}},{"key":"user_agent","value":{"stringValue":"Mozilla/5.0 (X11; Linux x86_64) AppleWebKit/537.36 (KHTML, like Gecko) HeadlessChrome/120.0.6099.28 Safari/537.36"}},{"key":"http.protocol","value":{"stringValue":"HTTP/1.1"}},{"key":"peer.address","value":{"stringValue":"172.18.0.24"}},{"key":"request_size","value":{"stringValue":"0"}},{"key":"response_size","value":{"stringValue":"177"}},{"key":"component","value":{"stringValue":"proxy"}},{"key":"upstream_cluster","value":{"stringValue":"frontend"}},{"key":"upstream_cluster.name","value":{"stringValue":"frontend"}},{"key":"http.status_code","value":{"stringValue":"200"}},{"key":"response_flags","value":{"stringValue":"-"}}],"status":{}},{"traceId":"a91f3eba35b33bc77664c27360740ede","spanId":"87b9899bc1bc2b91","parentSpanId":"599868287e218fae","name":"router frontend egress","kind":3,"startTimeUnixNano":"1724247952099844000","endTimeUnixNano":"1724247952170804000","attributes":[{"key":"http.protocol","value":{"stringValue":"HTTP/1.1"}},{"key":"upstream_address","value":{"stringValue":"172.18.0.23:8080"}},{"key":"peer.address","value":{"stringValue":"172.18.0.23:8080"}},{"key":"component","value":{"stringValue":"proxy"}},{"key":"upstream_cluster","value":{"stringValue":"frontend"}},{"key":"upstream_cluster.name","value":{"stringValue":"frontend"}},{"key":"http.status_code","value":{"stringValue":"200"}},{"key":"response_flags","value":{"stringValue":"-"}}],"status":{}}]}]},{"resource":{"attributes":[{"key":"docker.cli.cobra.command_path","value":{"stringValue":"docker%20compose"}},{"key":"service.name","value":{"stringValue":"frontend-proxy"}}]},"scopeSpans":[{"scope":{},"spans":[{"traceId":"149a5dbec0931c3ad98481ce379484da","spanId":"80571a7d42ead612","parentSpanId":"8cf67d9fe6eb71c7","name":"router frontend egress","kind":3,"startTimeUnixNano":"1724247951929304000","endTimeUnixNano":"1724247952017696000","attributes":[{"key":"http.protocol","value":{"stringValue":"HTTP/1.1"}},{"key":"upstream_address","value":{"stringValue":"172.18.0.23:8080"}},{"key":"peer.address","value":{"stringValue":"172.18.0.23:8080"}},{"key":"component","value":{"stringValue":"proxy"}},{"key":"upstream_cluster","value":{"stringValue":"frontend"}},{"key":"upstream_cluster.name","value":{"stringValue":"frontend"}},{"key":"http.status_code","value":{"stringValue":"200"}},{"key":"response_flags","value":{"stringValue":"-"}}],"status":{}},{"traceId":"149a5dbec0931c3ad98481ce379484da","spanId":"8cf67d9fe6eb71c7","parentSpanId":"02c03ec1bd92d2f8","name":"ingress","kind":2,"startTimeUnixNano":"1724247951929095000","endTimeUnixNano":"1724247952017734000","attributes":[{"key":"node_id","value":{"stringValue":""}},{"key":"zone","value":{"stringValue":""}},{"key":"guid:x-request-id","value":{"stringValue":"7befcaca-5b54-9612-9de7-010a6ea93a0a"}},{"key":"http.url","value":{"stringValue":"http://frontend-proxy:8080/"}},{"key":"http.method","value":{"stringValue":"GET"}},{"key":"downstream_cluster","value":{"stringValue":"-"}},{"key":"user_agent","value":{"stringValue":"python-requests/2.31.0"}},{"key":"http.protocol","value":{"stringValue":"HTTP/1.1"}},{"key":"peer.address","value":{"stringValue":"172.18.0.24"}},{"key":"request_size","value":{"stringValue":"0"}},{"key":"response_size","value":{"stringValue":"5909"}},{"key":"component","value":{"stringValue":"proxy"}},{"key":"upstream_cluster","value":{"stringValue":"frontend"}},{"key":"upstream_cluster.name","value":{"stringValue":"frontend"}},{"key":"http.status_code","value":{"stringValue":"200"}},{"key":"response_flags","value":{"stringValue":"-"}}],"status":{}},{"traceId":"b5772c17f5ce70d1040f123666a78bc3","spanId":"bc90a19c97bdf1d9","parentSpanId":"822ef63defb49998","name":"router frontend egress","kind":3,"startTimeUnixNano":"1724247952022048000","endTimeUnixNano":"1724247952165991000","attributes":[{"key":"http.protocol","value":{"stringValue":"HTTP/1.1"}},{"key":"upstream_address","value":{"stringValue":"172.18.0.23:8080"}},{"key":"peer.address","value":{"stringValue":"172.18.0.23:8080"}},{"key":"component","value":{"stringValue":"proxy"}},{"key":"upstream_cluster","value":{"stringValue":"frontend"}},{"key":"upstream_cluster.name","value":{"stringValue":"frontend"}},{"key":"http.status_code","value":{"stringValue":"200"}},{"key":"response_flags","value":{"stringValue":"-"}}],"status":{}},{"traceId":"b5772c17f5ce70d1040f123666a78bc3","spanId":"822ef63defb49998","parentSpanId":"12b9b10f3f32cb0e","name":"ingress","kind":2,"startTimeUnixNano":"1724247952021918000","endTimeUnixNano":"1724247952166019000","attributes":[{"key":"node_id","value":{"stringValue":""}},{"key":"zone","value":{"stringValue":""}},{"key":"guid:x-request-id","value":{"stringValue":"46ffa32f-dc68-9ef6-84e1-7816f7839392"}},{"key":"http.url","value":{"stringValue":"http://frontend-proxy:8080/api/products/66VCHSJNUP"}},{"key":"http.method","value":{"stringValue":"GET"}},{"key":"downstream_cluster","value":{"stringValue":"-"}},{"key":"user_agent","value":{"stringValue":"python-requests/2.31.0"}},{"key":"http.protocol","value":{"stringValue":"HTTP/1.1"}},{"key":"peer.address","value":{"stringValue":"172.18.0.24"}},{"key":"request_size","value":{"stringValue":"0"}},{"key":"response_size","value":{"stringValue":"498"}},{"key":"component","value":{"stringValue":"proxy"}},{"key":"upstream_cluster","value":{"stringValue":"frontend"}},{"key":"upstream_cluster.name","value":{"stringValue":"frontend"}},{"key":"http.status_code","value":{"stringValue":"200"}},{"key":"response_flags","value":{"stringValue":"-"}}],"status":{}},{"traceId":"39cd036fda537618e0f2b1ed708a5d8c","spanId":"05c2fce64ad49aa4","parentSpanId":"914b0058e4cc3525","name":"router frontend egress","kind":3,"startTimeUnixNano":"1724247952036130000","endTimeUnixNano":"1724247952193543000","attributes":[{"key":"http.protocol","value":{"stringValue":"HTTP/1.1"}},{"key":"upstream_address","value":{"stringValue":"172.18.0.23:8080"}},{"key":"peer.address","value":{"stringValue":"172.18.0.23:8080"}},{"key":"component","value":{"stringValue":"proxy"}},{"key":"upstream_cluster","value":{"stringValue":"frontend"}},{"key":"upstream_cluster.name","value":{"stringValue":"frontend"}},{"key":"http.status_code","value":{"stringValue":"200"}},{"key":"response_flags","value":{"stringValue":"-"}}],"status":{}}]}]}]}
{"resourceSpans":[{"resource":{"attributes":[{"key":"docker.cli.cobra.command_path","value":{"stringValue":"docker%20compose"}},{"key":"service.name","value":{"stringValue":"frontend-proxy"}}]},"scopeSpans":[{"scope":{},"spans":[{"traceId":"f93ec28b00b8abba8c935bcd5fa0f49a","spanId":"9838ca02d154f751","parentSpanId":"050fc92f47a9e463","name":"router imageprovider egress","kind":3,"startTimeUnixNano":"1724247952029459000","endTimeUnixNano":"1724247952030335000","attributes":[{"key":"http.protocol","value":{"stringValue":"HTTP/1.1"}},{"key":"upstream_address","value":{"stringValue":"172.18.0.12:8081"}},{"key":"peer.address","value":{"stringValue":"172.18.0.12:8081"}},{"key":"component","value":{"stringValue":"proxy"}},{"key":"upstream_cluster","value":{"stringValue":"imageprovider"}},{"key":"upstream_cluster.name","value":{"stringValue":"imageprovider"}},{"key":"http.status_code","value":{"stringValue":"200"}},{"key":"response_flags","value":{"stringValue":"-"}}],"status":{}},{"traceId":"f93ec28b00b8abba8c935bcd5fa0f49a","spanId":"050fc92f47a9e463","parentSpanId":"","name":"ingress","kind":2,"startTimeUnixNano":"1724247952029357000","endTimeUnixNano":"1724247952030385000","attributes":[{"key":"node_id","value":{"stringValue":""}},{"key":"zone","value":{"stringValue":""}},{"key":"guid:x-request-id","value":{"stringValue":"f2b0361e-9f22-9c2f-bd44-fb86751b27b3"}},{"key":"http.url","value":{"stringValue":"http://frontend-proxy:8080/images/opentelemetry-demo-logo.png"}},{"key":"http.method","value":{"stringValue":"GET"}},{"key":"downstream_cluster","value":{"stringValue":"-"}},{"key":"user_agent","value":{"stringValue":"Mozilla/5.0 (X11; Linux x86_64) AppleWebKit/537.36 (KHTML, like Gecko) HeadlessChrome/120.0.6099.28 Safari/537.36"}},{"key":"http.protocol","value":{"stringValue":"HTTP/1.1"}},{"key":"peer.address","value":{"stringValue":"172.18.0.24"}},{"key":"request_size","value":{"stringValue":"0"}},{"key":"response_size","value":{"stringValue":"100140"}},{"key":"component","value":{"stringValue":"proxy"}},{"key":"upstream_cluster","value":{"stringValue":"imageprovider"}},{"key":"upstream_cluster.name","value":{"stringValue":"imageprovider"}},{"key":"http.status_code","value":{"stringValue":"200"}},{"key":"response_flags","value":{"stringValue":"-"}}],"status":{}},{"traceId":"11bba2e1959720b104dabde7f25ce3d8","spanId":"ab331f07cc56bfda","parentSpanId":"7835899545fce704","name":"router frontend egress","kind":3,"startTimeUnixNano":"1724247952034253000","endTimeUnixNano":"1724247952195727000","attributes":[{"key":"http.protocol","value":{"stringValue":"HTTP/1.1"}},{"key":"upstream_address","value":{"stringValue":"172.18.0.23:8080"}},{"key":"peer.address","value":{"stringValue":"172.18.0.23:8080"}},{"key":"component","value":{"stringValue":"proxy"}},{"key":"upstream_cluster","value":{"stringValue":"frontend"}},{"key":"upstream_cluster.name","value":{"stringValue":"frontend"}},{"key":"http.status_code","value":{"stringValue":"200"}},{"key":"response_flags","value":{"stringValue":"-"}}],"status":{}},{"traceId":"11bba2e1959720b104dabde7f25ce3d8","spanId":"7835899545fce704","parentSpanId":"","name":"ingress","kind":2,"startTimeUnixNano":"1724247952034175000","endTimeUnixNano":"1724247952195758000","attributes":[{"key":"node_id","value":{"stringValue":""}},{"key":"zone","value":{"stringValue":""}},{"key":"guid:x-request-id","value":{"stringValue":"684bc8c5-6ff0-9179-84e6-2aa40585adfc"}},{"key":"http.url","value":{"stringValue":"http://frontend-proxy:8080/_next/static/chunks/framework-ecc4130bc7a58a64.js"}},{"key":"http.method","value":{"stringValue":"GET"}},{"key":"downstream_cluster","value":{"stringValue":"-"}},{"key":"user_agent","value":{"stringValue":"Mozilla/5.0 (X11; Linux x86_64) AppleWebKit/537.36 (KHTML, like Gecko) HeadlessChrome/120.0.6099.28 Safari/537.36"}},{"key":"http.protocol","value":{"stringValue":"HTTP/1.1"}},{"key":"peer.address","value":{"stringValue":"172.18.0.24"}},{"key":"request_size","value":{"stringValue":"0"}},{"key":"response_size","value":{"stringValue":"45267"}},{"key":"component","value":{"stringValue":"proxy"}},{"key":"upstream_cluster","value":{"stringValue":"frontend"}},{"key":"upstream_cluster.name","value":{"stringValue":"frontend"}},{"key":"http.status_code","value":{"stringValue":"200"}},{"key":"response_flags","value":{"stringValue":"-"}}],"status":{}},{"traceId":"deb7ba30609fd2ddb62b130671c6eae1","spanId":"80326e7719ad8716","parentSpanId":"293f9f6ff39aa5f0","name":"router frontend egress","kind":3,"startTimeUnixNano":"1724247952199508000","endTimeUnixNano":"1724247952203160000","attributes":[{"key":"http.protocol","value":{"stringValue":"HTTP/1.1"}},{"key":"upstream_address","value":{"stringValue":"172.18.0.23:8080"}},{"key":"peer.address","value":{"stringValue":"172.18.0.23:8080"}},{"key":"component","value":{"stringValue":"proxy"}},{"key":"upstream_cluster","value":{"stringValue":"frontend"}},{"key":"upstream_cluster.name","value":{"stringValue":"frontend"}},{"key":"http.status_code","value":{"stringValue":"200"}},{"key":"response_flags","value":{"stringValue":"-"}}],"status":{}}]}]},{"resource":{"attributes":[{"key":"docker.cli.cobra.command_path","value":{"stringValue":"docker%20compose"}},{"key":"service.name","value":{"stringValue":"frontend-proxy"}}]},"scopeSpans":[{"scope":{},"spans":[{"traceId":"a91f3eba35b33bc77664c27360740ede","spanId":"599868287e218fae","parentSpanId":"","name":"ingress","kind":2,"startTimeUnixNano":"1724247952099618000","endTimeUnixNano":"1724247952171858000","attributes":[{"key":"node_id","value":{"stringValue":""}},{"key":"zone","value":{"stringValue":""}},{"key":"guid:x-request-id","value":{"stringValue":"258ce487-0e90-99ee-a3f4-4fc52e294b08"}},{"key":"http.url","value":{"stringValue":"http://frontend-proxy:8080/_next/static/chunks/755-21e9a6edae71787e.js"}},{"key":"http.method","value":{"stringValue":"GET"}},{"key":"downstream_cluster","value":{"stringValue":"-"}},{"key":"user_agent","value":{"stringValue":"Mozilla/5.0 (X11; Linux x86_64) AppleWebKit/537.36 (KHTML, like Gecko) HeadlessChrome/120.0.6099.28 Safari/537.36"}},{"key":"http.protocol","value":{"stringValue":"HTTP/1.1"}},{"key":"peer.address","value":{"stringValue":"172.18.0.24"}},{"key":"request_size","value":{"stringValue":"0"}},{"key":"response_size","value":{"stringValue":"7134"}},{"key":"component","value":{"stringValue":"proxy"}},{"key":"upstream_cluster","value":{"stringValue":"frontend"}},{"key":"upstream_cluster.name","value":{"stringValue":"frontend"}},{"key":"http.status_code","value":{"stringValue":"200"}},{"key":"response_flags","value":{"stringValue":"-"}}],"status":{}},{"traceId":"dae720084fdd13bc8818fcc2db18991e","spanId":"a6a34931ba1497cd","parentSpanId":"9076cc8daf421361","name":"router frontend egress","kind":3,"startTimeUnixNano":"1724247952174193000","endTimeUnixNano":"1724247952196857000","attributes":[{"key":"http.protocol","value":{"stringValue":"HTTP/1.1"}},{"key":"upstream_address","value":{"stringValue":"172.18.0.23:8080"}},{"key":"peer.address","value":{"stringValue":"172.18.0.23:8080"}},{"key":"component","value":{"stringValue":"proxy"}},{"key":"upstream_cluster","value":{"stringValue":"frontend"}},{"key":"upstream_cluster.name","value":{"stringValue":"frontend"}},{"key":"http.status_code","value":{"stringValue":"200"}},{"key":"response_flags","value":{"stringValue":"-"}}],"status":{}},{"traceId":"dae720084fdd13bc8818fcc2db18991e","spanId":"9076cc8daf421361","parentSpanId":"","name":"ingress","kind":2,"startTimeUnixNano":"1724247952174029000","endTimeUnixNano":"1724247952196878000","attributes":[{"key":"node_id","value":{"stringValue":""}},{"key":"zone","value":{"stringValue":""}},{"key":"guid:x-request-id","value":{"stringValue":"d300e706-f930-97ea-9a14-9a9be622f022"}},{"key":"http.url","value":{"stringValue":"http://frontend-proxy:8080/_next/static/tKUWy_5CDFYHgnRQ-fYvZ/_buildManifest.js"}},{"key":"http.method","value":{"stringValue":"GET"}},{"key":"downstream_cluster","value":{"stringValue":"-"}},{"key":"user_agent","value":{"stringValue":"Mozilla/5.0 (X11; Linux x86_64) AppleWebKit/537.36 (KHTML, like Gecko) HeadlessChrome/120.0.6099.28 Safari/537.36"}},{"key":"http.protocol","value":{"stringValue":"HTTP/1.1"}},{"key":"peer.address","value":{"stringValue":"172.18.0.24"}},{"key":"request_size","value":{"stringValue":"0"}},{"key":"response_size","value":{"stringValue":"697"}},{"key":"component","value":{"stringValue":"proxy"}},{"key":"upstream_cluster","value":{"stringValue":"frontend"}},{"key":"upstream_cluster.name","value":{"stringValue":"frontend"}},{"key":"http.status_code","value":{"stringValue":"200"}},{"key":"response_flags","value":{"stringValue":"-"}}],"status":{}},{"traceId":"73e4d338b1ac94b76d454a3aace17d5b","spanId":"972173c13276a999","parentSpanId":"4b5c189b52b30abc","name":"router flagservice egress","kind":3,"startTimeUnixNano":"1724247952351430000","endTimeUnixNano":"1724247952353485000","attributes":[{"key":"http.protocol","value":{"stringValue":"HTTP/1.1"}},{"key":"upstream_address","value":{"stringValue":"172.18.0.3:8013"}},{"key":"peer.address","value":{"stringValue":"172.18.0.3:8013"}},{"key":"component","value":{"stringValue":"proxy"}},{"key":"upstream_cluster","value":{"stringValue":"flagservice"}},{"key":"upstream_cluster.name","value":{"stringValue":"flagservice"}},{"key":"http.status_code","value":{"stringValue":"200"}},{"key":"response_flags","value":{"stringValue":"-"}}],"status":{}},{"traceId":"73e4d338b1ac94b76d454a3aace17d5b","spanId":"4b5c189b52b30abc","parentSpanId":"9762d45e9794d9a5","name":"ingress","kind":2,"startTimeUnixNano":"1724247952351264000","endTimeUnixNano":"1724247952353509000","attributes":[{"key":"node_id","value":{"stringValue":""}},{"key":"zone","value":{"stringValue":""}},{"key":"guid:x-request-id","value":{"stringValue":"f4c60590-8b1b-93ae-b497-f1c6b5e4b144"}},{"key":"http.url","value":{"stringValue":"http://frontend-proxy:8080/flagservice/flagd.evaluation.v1.Service/ResolveAll"}},{"key":"http.method","value":{"stringValue":"POST"}},{"key":"downstream_cluster","value":{"stringValue":"-"}},{"key":"user_agent","value":{"stringValue":"Mozilla/5.0 (X11; Linux x86_64) AppleWebKit/537.36 (KHTML, like Gecko) HeadlessChrome/120.0.6099.28 Safari/537.36"}},{"key":"http.protocol","value":{"stringValue":"HTTP/1.1"}},{"key":"peer.address","value":{"stringValue":"172.18.0.24"}},{"key":"request_size","value":{"stringValue":"136"}},{"key":"response_size","value":{"stringValue":"243"}},{"key":"component","value":{"stringValue":"proxy"}},{"key":"upstream_cluster","value":{"stringValue":"flagservice"}},{"key":"upstream_cluster.name","value":{"stringValue":"flagservice"}},{"key":"http.status_code","value":{"stringValue":"200"}},{"key":"response_flags","value":{"stringValue":"-"}}],"status":{}}]}]},{"resource":{"attributes":[{"key":"docker.cli.cobra.command_path","value":{"stringValue":"docker%20compose"}},{"key":"telemetry.sdk.language","value":{"stringValue":"cpp"}},{"key":"service.name","value":{"stringValue":"currencyservice"}},{"key":"telemetry.sdk.version","value":{"stringValue":"1.15.0"}},{"key":"telemetry.sdk.name","value":{"stringValue":"opentelemetry"}}]},"scopeSpans":[{"scope":{"name":"currencyservice"},"spans":[{"traceId":"edf2c6ddf996c2ab5efe08ba4d3e4d15","spanId":"e3ae12d3bc97d2f8","parentSpanId":"d3e73af3861887a8","flags":1,"name":"CurrencyService/GetSupportedCurrencies","kind":2,"startTimeUnixNano":"1724247952370964528","endTimeUnixNano":"1724247952371918590","attributes":[{"key":"rpc.system","value":{"stringValue":"grpc"}},{"key":"rpc.service","value":{"stringValue":"oteldemo.CurrencyService"}},{"key":"rpc.method","value":{"stringValue":"GetSupportedCurrencies"}},{"key":"rpc.grpc.status_code","value":{"intValue":"0"}}],"events":[{"timeUnixNano":"1724247952370975998","name":"Processing supported currencies request"},{"timeUnixNano":"1724247952370987258","name":"Currencies fetched, response sent back"}],"status":{"code":1}}]}]},{"resource":{"attributes":[{"key":"docker.cli.cobra.command_path","value":{"stringValue":"docker%20compose"}},{"key":"service.name","value":{"stringValue":"frontend-proxy"}}]},"scopeSpans":[{"scope":{},"spans":[{"traceId":"376b7591c365544e3a10e56bac8ab776","spanId":"74a3d9211e19f046","parentSpanId":"3eec0b1c04a04c4c","name":"router frontend egress","kind":3,"startTimeUnixNano":"1724247952029556000","endTimeUnixNano":"1724247952156175000","attributes":[{"key":"http.protocol","value":{"stringValue":"HTTP/1.1"}},{"key":"upstream_address","value":{"stringValue":"172.18.0.23:8080"}},{"key":"peer.address","value":{"stringValue":"172.18.0.23:8080"}},{"key":"component","value":{"stringValue":"proxy"}},{"key":"upstream_cluster","value":{"stringValue":"frontend"}},{"key":"upstream_cluster.name","value":{"stringValue":"frontend"}},{"key":"http.status_code","value":{"stringValue":"200"}},{"key":"response_flags","value":{"stringValue":"-"}}],"status":{}},{"traceId":"376b7591c365544e3a10e56bac8ab776","spanId":"3eec0b1c04a04c4c","parentSpanId":"","name":"ingress","kind":2,"startTimeUnixNano":"1724247952029473000","endTimeUnixNano":"1724247952156266000","attributes":[{"key":"node_id","value":{"stringValue":""}},{"key":"zone","value":{"stringValue":""}},{"key":"guid:x-request-id","value":{"stringValue":"1d2be9dc-446a-9cae-a969-e91619343729"}},{"key":"http.url","value":{"stringValue":"http://frontend-proxy:8080/_next/static/chunks/webpack-f164db4954bac6ec.js"}},{"key":"http.method","value":{"stringValue":"GET"}},{"key":"downstream_cluster","value":{"stringValue":"-"}},{"key":"user_agent","value":{"stringValue":"Mozilla/5.0 (X11; Linux x86_64) AppleWebKit/537.36 (KHTML, like Gecko) HeadlessChrome/120.0.6099.28 Safari/537.36"}},{"key":"http.protocol","value":{"stringValue":"HTTP/1.1"}},{"key":"peer.address","value":{"stringValue":"172.18.0.24"}},{"key":"request_size","value":{"stringValue":"0"}},{"key":"response_size","value":{"stringValue":"829"}},{"key":"component","value":{"stringValue":"proxy"}},{"key":"upstream_cluster","value":{"stringValue":"frontend"}},{"key":"upstream_cluster.name","value":{"stringValue":"frontend"}},{"key":"http.status_code","value":{"stringValue":"200"}},{"key":"response_flags","value":{"stringValue":"-"}}],"status":{}},{"traceId":"0c8211679567556fe215ee22c4a39bb4","spanId":"af6ea921d259d3cd","parentSpanId":"8043569876a80a0a","name":"router frontend egress","kind":3,"startTimeUnixNano":"1724247952157545000","endTimeUnixNano":"1724247952198562000","attributes":[{"key":"http.protocol","value":{"stringValue":"HTTP/1.1"}},{"key":"upstream_address","value":{"stringValue":"172.18.0.23:8080"}},{"key":"peer.address","value":{"stringValue":"172.18.0.23:8080"}},{"key":"component","value":{"stringValue":"proxy"}},{"key":"upstream_cluster","value":{"stringValue":"frontend"}},{"key":"upstream_cluster.name","value":{"stringValue":"frontend"}},{"key":"http.status_code","value":{"stringValue":"200"}},{"key":"response_flags","value":{"stringValue":"-"}}],"status":{}},{"traceId":"0c8211679567556fe215ee22c4a39bb4","spanId":"8043569876a80a0a","parentSpanId":"","name":"ingress","kind":2,"startTimeUnixNano":"1724247952157394000","endTimeUnixNano":"1724247952198584000","attributes":[{"key":"node_id","value":{"stringValue":""}},{"key":"zone","value":{"stringValue":""}},{"key":"guid:x-request-id","value":{"stringValue":"7b65af86-431d-9498-89e6-8e63ac190e05"}},{"key":"http.url","value":{"stringValue":"http://frontend-proxy:8080/_next/static/chunks/867-dc50d089d3d82ad3.js"}},{"key":"http.method","value":{"stringValue":"GET"}},{"key":"downstream_cluster","value":{"stringValue":"-"}},{"key":"user_agent","value":{"stringValue":"Mozilla/5.0 (X11; Linux x86_64) AppleWebKit/537.36 (KHTML, like Gecko) HeadlessChrome/120.0.6099.28 Safari/537.36"}},{"key":"http.protocol","value":{"stringValue":"HTTP/1.1"}},{"key":"peer.address","value":{"stringValue":"172.18.0.24"}},{"key":"request_size","value":{"stringValue":"0"}},{"key":"response_size","value":{"stringValue":"3883"}},{"key":"component","value":{"stringValue":"proxy"}},{"key":"upstream_cluster","value":{"stringValue":"frontend"}},{"key":"upstream_cluster.name","value":{"stringValue":"frontend"}},{"key":"http.status_code","value":{"stringValue":"200"}},{"key":"response_flags","value":{"stringValue":"-"}}],"status":{}},{"traceId":"edf2c6ddf996c2ab5efe08ba4d3e4d15","spanId":"344eb2f834cb9c6d","parentSpanId":"ed6bffeb597a5401","name":"router frontend egress","kind":3,"startTimeUnixNano":"1724247952349026000","endTimeUnixNano":"1724247952376718000","attributes":[{"key":"http.protocol","value":{"stringValue":"HTTP/1.1"}},{"key":"upstream_address","value":{"stringValue":"172.18.0.23:8080"}},{"key":"peer.address","value":{"stringValue":"172.18.0.23:8080"}},{"key":"component","value":{"stringValue":"proxy"}},{"key":"upstream_cluster","value":{"stringValue":"frontend"}},{"key":"upstream_cluster.name","value":{"stringValue":"frontend"}},{"key":"http.status_code","value":{"stringValue":"200"}},{"key":"response_flags","value":{"stringValue":"-"}}],"status":{}}]}]},{"resource":{"attributes":[{"key":"docker.cli.cobra.command_path","value":{"stringValue":"docker%20compose"}},{"key":"service.name","value":{"stringValue":"frontend-proxy"}}]},"scopeSpans":[{"scope":{},"spans":[{"traceId":"269a763063f3667bbb7aa2ceda10c105","spanId":"6f7de2f976c14b05","parentSpanId":"9e0973532beff736","name":"router frontend egress","kind":3,"startTimeUnixNano":"1724247952033919000","endTimeUnixNano":"1724247952166893000","attributes":[{"key":"http.protocol","value":{"stringValue":"HTTP/1.1"}},{"key":"upstream_address","value":{"stringValue":"172.18.0.23:8080"}},{"key":"peer.address","value":{"stringValue":"172.18.0.23:8080"}},{"key":"component","value":{"stringValue":"proxy"}},{"key":"upstream_cluster","value":{"stringValue":"frontend"}},{"key":"upstream_cluster.name","value":{"stringValue":"frontend"}},{"key":"http.status_code","value":{"stringValue":"200"}},{"key":"response_flags","value":{"stringValue":"-"}}],"status":{}},{"traceId":"269a763063f3667bbb7aa2ceda10c105","spanId":"9e0973532beff736","parentSpanId":"","name":"ingress","kind":2,"startTimeUnixNano":"1724247952033713000","endTimeUnixNano":"1724247952166930000","attributes":[{"key":"node_id","value":{"stringValue":""}},{"key":"zone","value":{"stringValue":""}},{"key":"guid:x-request-id","value":{"stringValue":"11dd391e-52ab-91f6-a4b7-685b8b85095e"}},{"key":"http.url","value":{"stringValue":"http://frontend-proxy:8080/icons/Chevron.svg"}},{"key":"http.method","value":{"stringValue":"GET"}},{"key":"downstream_cluster","value":{"stringValue":"-"}},{"key":"user_agent","value":{"stringValue":"Mozilla/5.0 (X11; Linux x86_64) AppleWebKit/537.36 (KHTML, like Gecko) HeadlessChrome/120.0.6099.28 Safari/537.36"}},{"key":"http.protocol","value":{"stringValue":"HTTP/1.1"}},{"key":"peer.address","value":{"stringValue":"172.18.0.24"}},{"key":"request_size","value":{"stringValue":"0"}},{"key":"response_size","value":{"stringValue":"793"}},{"key":"component","value":{"stringValue":"proxy"}},{"key":"upstream_cluster","value":{"stringValue":"frontend"}},{"key":"upstream_cluster.name","value":{"stringValue":"frontend"}},{"key":"http.status_code","value":{"stringValue":"200"}},{"key":"response_flags","value":{"stringValue":"-"}}],"status":{}},{"traceId":"c5497102306a5a5241dae6be45dcd874","spanId":"997d68a282650618","parentSpanId":"2f4c123f55709e1d","name":"router frontend egress","kind":3,"startTimeUnixNano":"1724247952168560000","endTimeUnixNano":"1724247952199428000","attributes":[{"key":"http.protocol","value":{"stringValue":"HTTP/1.1"}},{"key":"upstream_address","value":{"stringValue":"172.18.0.23:8080"}},{"key":"peer.address","value":{"stringValue":"172.18.0.23:8080"}},{"key":"component","value":{"stringValue":"proxy"}},{"key":"upstream_cluster","value":{"stringValue":"frontend"}},{"key":"upstream_cluster.name","value":{"stringValue":"frontend"}},{"key":"http.status_code","value":{"stringValue":"200"}},{"key":"response_flags","value":{"stringValue":"-"}}],"status":{}},{"traceId":"c5497102306a5a5241dae6be45dcd874","spanId":"2f4c123f55709e1d","parentSpanId":"","name":"ingress","kind":2,"startTimeUnixNano":"1724247952168419000","endTimeUnixNano":"1724247952199466000","attributes":[{"key":"node_id","value":{"stringValue":""}},{"key":"zone","value":{"stringValue":""}},{"key":"guid:x-request-id","value":{"stringValue":"07ceb977-109c-9bb5-a155-fd0761bc50bc"}},{"key":"http.url","value":{"stringValue":"http://frontend-proxy:8080/_next/static/chunks/pages/cart-0ab51c052364106e.js"}},{"key":"http.method","value":{"stringValue":"GET"}},{"key":"downstream_cluster","value":{"stringValue":"-"}},{"key":"user_agent","value":{"stringValue":"Mozilla/5.0 (X11; Linux x86_64) AppleWebKit/537.36 (KHTML, like Gecko) HeadlessChrome/120.0.6099.28 Safari/537.36"}},{"key":"http.protocol","value":{"stringValue":"HTTP/1.1"}},{"key":"peer.address","value":{"stringValue":"172.18.0.24"}},{"key":"request_size","value":{"stringValue":"0"}},{"key":"response_size","value":{"stringValue":"3880"}},{"key":"component","value":{"stringValue":"proxy"}},{"key":"upstream_cluster","value":{"stringValue":"frontend"}},{"key":"upstream_cluster.name","value":{"stringValue":"frontend"}},{"key":"http.status_code","value":{"stringValue":"200"}},{"key":"response_flags","value":{"stringValue":"-"}}],"status":{}},{"traceId":"dd9c1f06a778ef1e305e6b9d9bf2f260","spanId":"858789a8ab4a0177","parentSpanId":"c9a9f7cdd01c4f7a","name":"router frontend egress","kind":3,"startTimeUnixNano":"1724247952347815000","endTimeUnixNano":"1724247952389559000","attributes":[{"key":"http.protocol","value":{"stringValue":"HTTP/1.1"}},{"key":"upstream_address","value":{"stringValue":"172.18.0.23:8080"}},{"key":"peer.address","value":{"stringValue":"172.18.0.23:8080"}},{"key":"component","value":{"stringValue":"proxy"}},{"key":"upstream_cluster","value":{"stringValue":"frontend"}},{"key":"upstream_cluster.name","value":{"stringValue":"frontend"}},{"key":"http.status_code","value":{"stringValue":"200"}},{"key":"response_flags","value":{"stringValue":"-"}}],"status":{}}]}]}]}
{"resourceSpans":[{"resource":{"attributes":[{"key":"docker.cli.cobra.command_path","value":{"stringValue":"docker%20compose"}},{"key":"telemetry.sdk.language","value":{"stringValue":"cpp"}},{"key":"service.name","value":{"stringValue":"currencyservice"}},{"key":"telemetry.sdk.version","value":{"stringValue":"1.15.0"}},{"key":"telemetry.sdk.name","value":{"stringValue":"opentelemetry"}}]},"scopeSpans":[{"scope":{"name":"currencyservice"},"spans":[{"traceId":"a6a9488dd3f37a11c721cdcf439a3f78","spanId":"d1e4a7e223bec67c","parentSpanId":"aa14b2116ee4331e","flags":1,"name":"CurrencyService/Convert","kind":2,"startTimeUnixNano":"1724247952450833377","endTimeUnixNano":"1724247952452495961","attributes":[{"key":"rpc.system","value":{"stringValue":"grpc"}},{"key":"rpc.service","value":{"stringValue":"oteldemo.CurrencyService"}},{"key":"rpc.method","value":{"stringValue":"Convert"}},{"key":"rpc.grpc.status_code","value":{"intValue":"0"}},{"key":"app.currency.conversion.from","value":{"stringValue":"USD"}},{"key":"app.currency.conversion.to","value":{"stringValue":"CHF"}}],"events":[{"timeUnixNano":"1724247952450839897","name":"Processing currency conversion request"},{"timeUnixNano":"1724247952450883488","name":"Conversion successful, response sent back"}],"status":{"code":1}}]}]},{"resource":{"attributes":[{"key":"docker.cli.cobra.command_path","value":{"stringValue":"docker%20compose"}},{"key":"telemetry.sdk.language","value":{"stringValue":"cpp"}},{"key":"service.name","value":{"stringValue":"currencyservice"}},{"key":"telemetry.sdk.version","value":{"stringValue":"1.15.0"}},{"key":"telemetry.sdk.name","value":{"stringValue":"opentelemetry"}}]},"scopeSpans":[{"scope":{"name":"currencyservice"},"spans":[{"traceId":"a6a9488dd3f37a11c721cdcf439a3f78","spanId":"5f4259894805aa9a","parentSpanId":"d69d806f6200648d","flags":1,"name":"CurrencyService/Convert","kind":2,"startTimeUnixNano":"1724247952451053736","endTimeUnixNano":"1724247952453665869","attributes":[{"key":"rpc.system","value":{"stringValue":"grpc"}},{"key":"rpc.service","value":{"stringValue":"oteldemo.CurrencyService"}},{"key":"rpc.method","value":{"stringValue":"Convert"}},{"key":"rpc.grpc.status_code","value":{"intValue":"0"}},{"key":"app.currency.conversion.from","value":{"stringValue":"USD"}},{"key":"app.currency.conversion.to","value":{"stringValue":"CHF"}}],"events":[{"timeUnixNano":"1724247952451064886","name":"Processing currency conversion request"},{"timeUnixNano":"1724247952451634900","name":"Conversion successful, response sent back"}],"status":{"code":1}}]}]},{"resource":{"attributes":[{"key":"docker.cli.cobra.command_path","value":{"stringValue":"docker%20compose"}},{"key":"service.name","value":{"stringValue":"frontend-proxy"}}]},"scopeSpans":[{"scope":{},"spans":[{"traceId":"deb7ba30609fd2ddb62b130671c6eae1","spanId":"293f9f6ff39aa5f0","parentSpanId":"","name":"ingress","kind":2,"startTimeUnixNano":"1724247952199360000","endTimeUnixNano":"1724247952203601000","attributes":[{"key":"node_id","value":{"stringValue":""}},{"key":"zone","value":{"stringValue":""}},{"key":"guid:x-request-id","value":{"stringValue":"fff71124-577c-9949-aaf1-49d798bbf67b"}},{"key":"http.url","value":{"stringValue":"http://frontend-proxy:8080/_next/static/tKUWy_5CDFYHgnRQ-fYvZ/_ssgManifest.js"}},{"key":"http.method","value":{"stringValue":"GET"}},{"key":"downstream_cluster","value":{"stringValue":"-"}},{"key":"user_agent","value":{"stringValue":"Mozilla/5.0 (X11; Linux x86_64) AppleWebKit/537.36 (KHTML, like Gecko) HeadlessChrome/120.0.6099.28 Safari/537.36"}},{"key":"http.protocol","value":{"stringValue":"HTTP/1.1"}},{"key":"peer.address","value":{"stringValue":"172.18.0.24"}},{"key":"request_size","value":{"stringValue":"0"}},{"key":"response_size","value":{"stringValue":"77"}},{"key":"component","value":{"stringValue":"proxy"}},{"key":"upstream_cluster","value":{"stringValue":"frontend"}},{"key":"upstream_cluster.name","value":{"stringValue":"frontend"}},{"key":"http.status_code","value":{"stringValue":"200"}},{"key":"response_flags","value":{"stringValue":"-"}}],"status":{}},{"traceId":"e5e1a34f483b0a88a7372ff42835cb4b","spanId":"f74fbac55181c939","parentSpanId":"1de8faba94aac121","name":"router frontend egress","kind":3,"startTimeUnixNano":"1724247952345829000","endTimeUnixNano":"1724247952410849000","attributes":[{"key":"http.protocol","value":{"stringValue":"HTTP/1.1"}},{"key":"upstream_address","value":{"stringValue":"172.18.0.23:8080"}},{"key":"peer.address","value":{"stringValue":"172.18.0.23:8080"}},{"key":"component","value":{"stringValue":"proxy"}},{"key":"upstream_cluster","value":{"stringValue":"frontend"}},{"key":"upstream_cluster.name","value":{"stringValue":"frontend"}},{"key":"http.status_code","value":{"stringValue":"200"}},{"key":"response_flags","value":{"stringValue":"-"}}],"status":{}},{"traceId":"e5e1a34f483b0a88a7372ff42835cb4b","spanId":"1de8faba94aac121","parentSpanId":"1b96d183ecef3cf7","name":"ingress","kind":2,"startTimeUnixNano":"1724247952345673000","endTimeUnixNano":"1724247952410888000","attributes":[{"key":"node_id","value":{"stringValue":""}},{"key":"zone","value":{"stringValue":""}},{"key":"guid:x-request-id","value":{"stringValue":"5ab25030-a311-92e0-8bc3-5a59c26bf253"}},{"key":"http.url","value":{"stringValue":"http://frontend-proxy:8080/api/recommendations?productIds=\u0026sessionId=dec6174d-716e-4122-bd93-05f9c4b4e1a8\u0026currencyCode="}},{"key":"http.method","value":{"stringValue":"GET"}},{"key":"downstream_cluster","value":{"stringValue":"-"}},{"key":"user_agent","value":{"stringValue":"Mozilla/5.0 (X11; Linux x86_64) AppleWebKit/537.36 (KHTML, like Gecko) HeadlessChrome/120.0.6099.28 Safari/537.36"}},{"key":"http.protocol","value":{"stringValue":"HTTP/1.1"}},{"key":"peer.address","value":{"stringValue":"172.18.0.24"}},{"key":"request_size","value":{"stringValue":"0"}},{"key":"response_size","value":{"stringValue":"1394"}},{"key":"component","value":{"stringValue":"proxy"}},{"key":"upstream_cluster","value":{"stringValue":"frontend"}},{"key":"upstream_cluster.name","value":{"stringValue":"frontend"}},{"key":"http.status_code","value":{"stringValue":"200"}},{"key":"response_flags","value":{"stringValue":"-"}}],"status":{}},{"traceId":"ca725541c370e42e4fdc90213cae41b4","spanId":"5e9ba70e71ec1541","parentSpanId":"c573e70fab2b227f","name":"router frontend egress","kind":3,"startTimeUnixNano":"1724247952437751000","endTimeUnixNano":"1724247952454161000","attributes":[{"key":"http.protocol","value":{"stringValue":"HTTP/1.1"}},{"key":"upstream_address","value":{"stringValue":"172.18.0.23:8080"}},{"key":"peer.address","value":{"stringValue":"172.18.0.23:8080"}},{"key":"component","value":{"stringValue":"proxy"}},{"key":"upstream_cluster","value":{"stringValue":"frontend"}},{"key":"upstream_cluster.name","value":{"stringValue":"frontend"}},{"key":"http.status_code","value":{"stringValue":"200"}},{"key":"response_flags","value":{"stringValue":"-"}}],"status":{}},{"traceId":"ca725541c370e42e4fdc90213cae41b4","spanId":"c573e70fab2b227f","parentSpanId":"","name":"ingress","kind":2,"startTimeUnixNano":"1724247952437554000","endTimeUnixNano":"1724247952454196000","attributes":[{"key":"node_id","value":{"stringValue":""}},{"key":"zone","value":{"stringValue":""}},{"key":"guid:x-request-id","value":{"stringValue":"de352a4f-ae17-9780-ac10-218cf2b59b0a"}},{"key":"http.url","value":{"stringValue":"http://frontend-proxy:8080/_next/static/chunks/pages/index-bb68a53a05f54407.js"}},{"key":"http.method","value":{"stringValue":"GET"}},{"key":"downstream_cluster","value":{"stringValue":"-"}},{"key":"user_agent","value":{"stringValue":"Mozilla/5.0 (X11; Linux x86_64) AppleWebKit/537.36 (KHTML, like Gecko) HeadlessChrome/120.0.6099.28 Safari/537.36"}},{"key":"http.protocol","value":{"stringValue":"HTTP/1.1"}},{"key":"peer.address","value":{"stringValue":"172.18.0.24"}},{"key":"request_size","value":{"stringValue":"0"}},{"key":"response_size","value":{"stringValue":"1203"}},{"key":"component","value":{"stringValue":"proxy"}},{"key":"upstream_cluster","value":{"stringValue":"frontend"}},{"key":"upstream_cluster.name","value":{"stringValue":"frontend"}},{"key":"http.status_code","value":{"stringValue":"200"}},{"key":"response_flags","value":{"stringValue":"-"}}],"status":{}}]}]},{"resource":{"attributes":[{"key":"docker.cli.cobra.command_path","value":{"stringValue":"docker%20compose"}},{"key":"telemetry.sdk.language","value":{"stringValue":"cpp"}},{"key":"service.name","value":{"stringValue":"currencyservice"}},{"key":"telemetry.sdk.version","value":{"stringValue":"1.15.0"}},{"key":"telemetry.sdk.name","value":{"stringValue":"opentelemetry"}}]},"scopeSpans":[{"scope":{"name":"currencyservice"},"spans":[{"traceId":"a6a9488dd3f37a11c721cdcf439a3f78","spanId":"aabfd424bb1c4a8f","parentSpanId":"1313a890f202b91f","flags":1,"name":"CurrencyService/Convert","kind":2,"startTimeUnixNano":"1724247952451065615","endTimeUnixNano":"1724247952454603406","attributes":[{"key":"rpc.system","value":{"stringValue":"grpc"}},{"key":"rpc.service","value":{"stringValue":"oteldemo.CurrencyService"}},{"key":"rpc.method","value":{"stringValue":"Convert"}},{"key":"rpc.grpc.status_code","value":{"intValue":"0"}},{"key":"app.currency.conversion.from","value":{"stringValue":"USD"}},{"key":"app.currency.conversion.to","value":{"stringValue":"CHF"}}],"events":[{"timeUnixNano":"1724247952451076635","name":"Processing currency conversion request"},{"timeUnixNano":"1724247952451692687","name":"Conversion successful, response sent back"}],"status":{"code":1}}]}]},{"resource":{"attributes":[{"key":"docker.cli.cobra.command_path","value":{"stringValue":"docker%20compose"}},{"key":"telemetry.sdk.language","value":{"stringValue":"cpp"}},{"key":"service.name","value":{"stringValue":"currencyservice"}},{"key":"telemetry.sdk.version","value":{"stringValue":"1.15.0"}},{"key":"telemetry.sdk.name","value":{"stringValue":"opentelemetry"}}]},"scopeSpans":[{"scope":{"name":"currencyservice"},"spans":[{"traceId":"a6a9488dd3f37a11c721cdcf439a3f78","spanId":"576bf7fc5e84112d","parentSpanId":"408fb1e813df7e62","flags":1,"name":"CurrencyService/Convert","kind":2,"startTimeUnixNano":"1724247952451728508","endTimeUnixNano":"1724247952455999789","attributes":[{"key":"rpc.system","value":{"stringValue":"grpc"}},{"key":"rpc.service","value":{"stringValue":"oteldemo.CurrencyService"}},{"key":"rpc.method","value":{"stringValue":"Convert"}},{"key":"rpc.grpc.status_code","value":{"intValue":"0"}},{"key":"app.currency.conversion.from","value":{"stringValue":"USD"}},{"key":"app.currency.conversion.to","value":{"stringValue":"CHF"}}],"events":[{"timeUnixNano":"1724247952451734388","name":"Processing currency conversion request"},{"timeUnixNano":"1724247952451760659","name":"Conversion successful, response sent back"}],"status":{"code":1}}]}]},{"resource":{"attributes":[{"key":"docker.cli.cobra.command_path","value":{"stringValue":"docker%20compose"}},{"key":"service.name","value":{"stringValue":"frontend-proxy"}}]},"scopeSpans":[{"scope":{},"spans":[{"traceId":"edf2c6ddf996c2ab5efe08ba4d3e4d15","spanId":"ed6bffeb597a5401","parentSpanId":"dc1c222c9c03714c","name":"ingress","kind":2,"startTimeUnixNano":"1724247952348896000","endTimeUnixNano":"1724247952377372000","attributes":[{"key":"node_id","value":{"stringValue":""}},{"key":"zone","value":{"stringValue":""}},{"key":"guid:x-request-id","value":{"stringValue":"c8527c7f-4625-9494-9971-82abdc2cf7b4"}},{"key":"http.url","value":{"stringValue":"http://frontend-proxy:8080/api/currency?"}},{"key":"http.method","value":{"stringValue":"GET"}},{"key":"downstream_cluster","value":{"stringValue":"-"}},{"key":"user_agent","value":{"stringValue":"Mozilla/5.0 (X11; Linux x86_64) AppleWebKit/537.36 (KHTML, like Gecko) HeadlessChrome/120.0.6099.28 Safari/537.36"}},{"key":"http.protocol","value":{"stringValue":"HTTP/1.1"}},{"key":"peer.address","value":{"stringValue":"172.18.0.24"}},{"key":"request_size","value":{"stringValue":"0"}},{"key":"response_size","value":{"stringValue":"199"}},{"key":"component","value":{"stringValue":"proxy"}},{"key":"upstream_cluster","value":{"stringValue":"frontend"}},{"key":"upstream_cluster.name","value":{"stringValue":"frontend"}},{"key":"http.status_code","value":{"stringValue":"200"}},{"key":"response_flags","value":{"stringValue":"-"}}],"status":{}},{"traceId":"6b31dcdb9ea594a95e6d32c6d57013e6","spanId":"5d992c527f527a6c","parentSpanId":"36d9f63aba26ddc6","name":"router frontend egress","kind":3,"startTimeUnixNano":"1724247952396175000","endTimeUnixNano":"1724247952419385000","attributes":[{"key":"http.protocol","value":{"stringValue":"HTTP/1.1"}},{"key":"upstream_address","value":{"stringValue":"172.18.0.23:8080"}},{"key":"peer.address","value":{"stringValue":"172.18.0.23:8080"}},{"key":"component","value":{"stringValue":"proxy"}},{"key":"upstream_cluster","value":{"stringValue":"frontend"}},{"key":"upstream_cluster.name","value":{"stringValue":"frontend"}},{"key":"http.status_code","value":{"stringValue":"200"}},{"key":"response_flags","value":{"stringValue":"-"}}],"status":{}},{"traceId":"6b31dcdb9ea594a95e6d32c6d57013e6","spanId":"36d9f63aba26ddc6","parentSpanId":"68d1eb133f48efee","name":"ingress","kind":2,"startTimeUnixNano":"1724247952396010000","endTimeUnixNano":"1724247952419423000","attributes":[{"key":"node_id","value":{"stringValue":""}},{"key":"zone","value":{"stringValue":""}},{"key":"guid:x-request-id","value":{"stringValue":"08614d45-20d2-971d-839b-ef94a0bc8b2b"}},{"key":"http.url","value":{"stringValue":"http://frontend-proxy:8080/api/cart?sessionId=dec6174d-716e-4122-bd93-05f9c4b4e1a8\u0026currencyCode=USD"}},{"key":"http.method","value":{"stringValue":"GET"}},{"key":"downstream_cluster","value":{"stringValue":"-"}},{"key":"user_agent","value":{"stringValue":"Mozilla/5.0 (X11; Linux x86_64) AppleWebKit/537.36 (KHTML, like Gecko) HeadlessChrome/120.0.6099.28 Safari/537.36"}},{"key":"http.protocol","value":{"stringValue":"HTTP/1.1"}},{"key":"peer.address","value":{"stringValue":"172.18.0.24"}},{"key":"request_size","value":{"stringValue":"0"}},{"key":"response_size","value":{"stringValue":"24"}},{"key":"component","value":{"stringValue":"proxy"}},{"key":"upstream_cluster","value":{"stringValue":"frontend"}},{"key":"upstream_cluster.name","value":{"stringValue":"frontend"}},{"key":"http.status_code","value":{"stringValue":"200"}},{"key":"response_flags","value":{"stringValue":"-"}}],"status":{}},{"traceId":"a6a9488dd3f37a11c721cdcf439a3f78","spanId":"d52f293e9d270444","parentSpanId":"633e12d944dfeb0c","name":"router frontend egress","kind":3,"startTimeUnixNano":"1724247952424755000","endTimeUnixNano":"1724247952460382000","attributes":[{"key":"http.protocol","value":{"stringValue":"HTTP/1.1"}},{"key":"upstream_address","value":{"stringValue":"172.18.0.23:8080"}},{"key":"peer.address","value":{"stringValue":"172.18.0.23:8080"}},{"key":"component","value":{"stringValue":"proxy"}},{"key":"upstream_cluster","value":{"stringValue":"frontend"}},{"key":"upstream_cluster.name","value":{"stringValue":"frontend"}},{"key":"http.status_code","value":{"stringValue":"200"}},{"key":"response_flags","value":{"stringValue":"-"}}],"status":{}},{"traceId":"a6a9488dd3f37a11c721cdcf439a3f78","spanId":"633e12d944dfeb0c","parentSpanId":"cc4378671196d5c0","name":"ingress","kind":2,"startTimeUnixNano":"1724247952424581000","endTimeUnixNano":"1724247952460415000","attributes":[{"key":"node_id","value":{"stringValue":""}},{"key":"zone","value":{"stringValue":""}},{"key":"guid:x-request-id","value":{"stringValue":"36b102aa-60b2-9e98-b50f-911d04abf1e1"}},{"key":"http.url","value":{"stringValue":"http://frontend-proxy:8080/api/recommendations?productIds=\u0026sessionId=dec6174d-716e-4122-bd93-05f9c4b4e1a8\u0026currencyCode=CHF"}},{"key":"http.method","value":{"stringValue":"GET"}},{"key":"downstream_cluster","value":{"stringValue":"-"}},{"key":"user_agent","value":{"stringValue":"Mozilla/5.0 (X11; Linux x86_64) AppleWebKit/537.36 (KHTML, like Gecko) HeadlessChrome/120.0.6099.28 Safari/537.36"}},{"key":"http.protocol","value":{"stringValue":"HTTP/1.1"}},{"key":"peer.address","value":{"stringValue":"172.18.0.24"}},{"key":"request_size","value":{"stringValue":"0"}},{"key":"response_size","value":{"stringValue":"1096"}},{"key":"component","value":{"stringValue":"proxy"}},{"key":"upstream_cluster","value":{"stringValue":"frontend"}},{"key":"upstream_cluster.name","value":{"stringValue":"frontend"}},{"key":"http.status_code","value":{"stringValue":"200"}},{"key":"response_flags","value":{"stringValue":"-"}}],"status":{}}]}]},{"resource":{"attributes":[{"key":"docker.cli.cobra.command_path","value":{"stringValue":"docker%20compose"}},{"key":"service.name","value":{"stringValue":"frontend-proxy"}}]},"scopeSpans":[{"scope":{},"spans":[{"traceId":"89a51f085242cdad06f5147668084101","spanId":"4b5ea8ad8a485889","parentSpanId":"91570c966dc2fd6d","name":"router imageprovider egress","kind":3,"startTimeUnixNano":"1724247952476915000","endTimeUnixNano":"1724247952477630000","attributes":[{"key":"http.protocol","value":{"stringValue":"HTTP/1.1"}},{"key":"upstream_address","value":{"stringValue":"172.18.0.12:8081"}},{"key":"peer.address","value":{"stringValue":"172.18.0.12:8081"}},{"key":"component","value":{"stringValue":"proxy"}},{"key":"upstream_cluster","value":{"stringValue":"imageprovider"}},{"key":"upstream_cluster.name","value":{"stringValue":"imageprovider"}},{"key":"http.status_code","value":{"stringValue":"200"}},{"key":"response_flags","value":{"stringValue":"-"}}],"status":{}},{"traceId":"89a51f085242cdad06f5147668084101","spanId":"91570c966dc2fd6d","parentSpanId":"0763063d202a3128","name":"ingress","kind":2,"startTimeUnixNano":"1724247952476695000","endTimeUnixNano":"1724247952477672000","attributes":[{"key":"node_id","value":{"stringValue":""}},{"key":"zone","value":{"stringValue":""}},{"key":"guid:x-request-id","value":{"stringValue":"f7569b65-3ffd-9e88-a1cb-a60256165c7d"}},{"key":"http.url","value":{"stringValue":"http://frontend-proxy:8080/images/products/NationalParkFoundationExplorascope.jpg"}},{"key":"http.method","value":{"stringValue":"GET"}},{"key":"downstream_cluster","value":{"stringValue":"-"}},{"key":"user_agent","value":{"stringValue":"Mozilla/5.0 (X11; Linux x86_64) AppleWebKit/537.36 (KHTML, like Gecko) HeadlessChrome/120.0.6099.28 Safari/537.36"}},{"key":"http.protocol","value":{"stringValue":"HTTP/1.1"}},{"key":"peer.address","value":{"stringValue":"172.18.0.24"}},{"key":"request_size","value":{"stringValue":"0"}},{"key":"response_size","value":{"stringValue":"21650"}},{"key":"component","value":{"stringValue":"proxy"}},{"key":"upstream_cluster","value":{"stringValue":"imageprovider"}},{"key":"upstream_cluster.name","value":{"stringValue":"imageprovider"}},{"key":"http.status_code","value":{"stringValue":"200"}},{"key":"response_flags","value":{"stringValue":"-"}}],"status":{}},{"traceId":"566482dd893afd95a22a52089da36669","spanId":"2bf07e8085a17805","parentSpanId":"f95daf41d7436e31","name":"router imageprovider egress","kind":3,"startTimeUnixNano":"1724247952479250000","endTimeUnixNano":"1724247952479659000","attributes":[{"key":"http.protocol","value":{"stringValue":"HTTP/1.1"}},{"key":"upstream_address","value":{"stringValue":"172.18.0.12:8081"}},{"key":"peer.address","value":{"stringValue":"172.18.0.12:8081"}},{"key":"component","value":{"stringValue":"proxy"}},{"key":"upstream_cluster","value":{"stringValue":"imageprovider"}},{"key":"upstream_cluster.name","value":{"stringValue":"imageprovider"}},{"key":"http.status_code","value":{"stringValue":"200"}},{"key":"response_flags","value":{"stringValue":"-"}}],"status":{}},{"traceId":"566482dd893afd95a22a52089da36669","spanId":"f95daf41d7436e31","parentSpanId":"bd7442f46ea0e65b","name":"ingress","kind":2,"startTimeUnixNano":"1724247952479131000","endTimeUnixNano":"1724247952479674000","attributes":[{"key":"node_id","value":{"stringValue":""}},{"key":"zone","value":{"stringValue":""}},{"key":"guid:x-request-id","value":{"stringValue":"33c44027-46d0-90d4-bb4d-c5973f9293ec"}},{"key":"http.url","value":{"stringValue":"http://frontend-proxy:8080/images/products/SolarFilter.jpg"}},{"key":"http.method","value":{"stringValue":"GET"}},{"key":"downstream_cluster","value":{"stringValue":"-"}},{"key":"user_agent","value":{"stringValue":"Mozilla/5.0 (X11; Linux x86_64) AppleWebKit/537.36 (KHTML, like Gecko) HeadlessChrome/120.0.6099.28 Safari/537.36"}},{"key":"http.protocol","value":{"stringValue":"HTTP/1.1"}},{"key":"peer.address","value":{"stringValue":"172.18.0.24"}},{"key":"request_size","value":{"stringValue":"0"}},{"key":"response_size","value":{"stringValue":"105955"}},{"key":"component","value":{"stringValue":"proxy"}},{"key":"upstream_cluster","value":{"stringValue":"imageprovider"}},{"key":"upstream_cluster.name","value":{"stringValue":"imageprovider"}},{"key":"http.status_code","value":{"stringValue":"200"}},{"key":"response_flags","value":{"stringValue":"-"}}],"status":{}},{"traceId":"3fe291b298c6e5f1e6fbea0e7b21c829","spanId":"5e5b73491a403d0f","parentSpanId":"d779bfa8c05f32c6","name":"router imageprovider egress","kind":3,"startTimeUnixNano":"1724247952484577000","endTimeUnixNano":"1724247952485283000","attributes":[{"key":"http.protocol","value":{"stringValue":"HTTP/1.1"}},{"key":"upstream_address","value":{"stringValue":"172.18.0.12:8081"}},{"key":"peer.address","value":{"stringValue":"172.18.0.12:8081"}},{"key":"component","value":{"stringValue":"proxy"}},{"key":"upstream_cluster","value":{"stringValue":"imageprovider"}},{"key":"upstream_cluster.name","value":{"stringValue":"imageprovider"}},{"key":"http.status_code","value":{"stringValue":"200"}},{"key":"response_flags","value":{"stringValue":"-"}}],"status":{}}]}]},{"resource":{"attributes":[{"key":"docker.cli.cobra.command_path","value":{"stringValue":"docker%20compose"}},{"key":"service.name","value":{"stringValue":"frontend-proxy"}}]},"scopeSpans":[{"scope":{},"spans":[{"traceId":"3fe291b298c6e5f1e6fbea0e7b21c829","spanId":"d779bfa8c05f32c6","parentSpanId":"9c980d9dd87a0af4","name":"ingress","kind":2,"startTimeUnixNano":"1724247952484408000","endTimeUnixNano":"1724247952485472000","attributes":[{"key":"node_id","value":{"stringValue":""}},{"key":"zone","value":{"stringValue":""}},{"key":"guid:x-request-id","value":{"stringValue":"0f5cc7c8-b313-9fc2-a15e-f400c3047dbc"}},{"key":"http.url","value":{"stringValue":"http://frontend-proxy:8080/images/products/RedFlashlight.jpg"}},{"key":"http.method","value":{"stringValue":"GET"}},{"key":"downstream_cluster","value":{"stringValue":"-"}},{"key":"user_agent","value":{"stringValue":"Mozilla/5.0 (X11; Linux x86_64) AppleWebKit/537.36 (KHTML, like Gecko) HeadlessChrome/120.0.6099.28 Safari/537.36"}},{"key":"http.protocol","value":{"stringValue":"HTTP/1.1"}},{"key":"peer.address","value":{"stringValue":"172.18.0.24"}},{"key":"request_size","value":{"stringValue":"0"}},{"key":"response_size","value":{"stringValue":"369585"}},{"key":"component","value":{"stringValue":"proxy"}},{"key":"upstream_cluster","value":{"stringValue":"imageprovider"}},{"key":"upstream_cluster.name","value":{"stringValue":"imageprovider"}},{"key":"http.status_code","value":{"stringValue":"200"}},{"key":"response_flags","value":{"stringValue":"-"}}],"status":{}},{"traceId":"d1f0b42f24e865dd240c459423edb3d2","spanId":"09f2a9cc3ace1a10","parentSpanId":"1b95a73160aa2a8c","name":"router frontend egress","kind":3,"startTimeUnixNano":"1724247952501837000","endTimeUnixNano":"1724247952505182000","attributes":[{"key":"http.protocol","value":{"stringValue":"HTTP/1.1"}},{"key":"upstream_address","value":{"stringValue":"172.18.0.23:8080"}},{"key":"peer.address","value":{"stringValue":"172.18.0.23:8080"}},{"key":"component","value":{"stringValue":"proxy"}},{"key":"upstream_cluster","value":{"stringValue":"frontend"}},{"key":"upstream_cluster.name","value":{"stringValue":"frontend"}},{"key":"http.status_code","value":{"stringValue":"200"}},{"key":"response_flags","value":{"stringValue":"-"}}],"status":{}},{"traceId":"d1f0b42f24e865dd240c459423edb3d2","spanId":"1b95a73160aa2a8c","parentSpanId":"","name":"ingress","kind":2,"startTimeUnixNano":"1724247952501638000","endTimeUnixNano":"1724247952505227000","attributes":[{"key":"node_id","value":{"stringValue":""}},{"key":"zone","value":{"stringValue":""}},{"key":"guid:x-request-id","value":{"stringValue":"4a55ecc3-6acb-92e0-b27b-890ba664db86"}},{"key":"http.url","value":{"stringValue":"http://frontend-proxy:8080/_next/static/chunks/pages/product/%5BproductId%5D-e419d8e486a0719c.js"}},{"key":"http.method","value":{"stringValue":"GET"}},{"key":"downstream_cluster","value":{"stringValue":"-"}},{"key":"user_agent","value":{"stringValue":"Mozilla/5.0 (X11; Linux x86_64) AppleWebKit/537.36 (KHTML, like Gecko) HeadlessChrome/120.0.6099.28 Safari/537.36"}},{"key":"http.protocol","value":{"stringValue":"HTTP/1.1"}},{"key":"peer.address","value":{"stringValue":"172.18.0.24"}},{"key":"request_size","value":{"stringValue":"0"}},{"key":"response_size","value":{"stringValue":"2360"}},{"key":"component","value":{"stringValue":"proxy"}},{"key":"upstream_cluster","value":{"stringValue":"frontend"}},{"key":"upstream_cluster.name","value":{"stringValue":"frontend"}},{"key":"http.status_code","value":{"stringValue":"200"}},{"key":"response_flags","value":{"stringValue":"-"}}],"status":{}},{"traceId":"8cf50611c71e24f81e5e4d3000bde113","spanId":"9044e09dbc7bf5e2","parentSpanId":"0bffe8e992ea29d2","name":"router frontend egress","kind":3,"startTimeUnixNano":"1724247952511091000","endTimeUnixNano":"1724247952513498000","attributes":[{"key":"http.protocol","value":{"stringValue":"HTTP/1.1"}},{"key":"upstream_address","value":{"stringValue":"172.18.0.23:8080"}},{"key":"peer.address","value":{"stringValue":"172.18.0.23:8080"}},{"key":"component","value":{"stringValue":"proxy"}},{"key":"upstream_cluster","value":{"stringValue":"frontend"}},{"key":"upstream_cluster.name","value":{"stringValue":"frontend"}},{"key":"http.status_code","value":{"stringValue":"200"}},{"key":"response_flags","value":{"stringValue":"-"}}],"status":{}},{"traceId":"8cf50611c71e24f81e5e4d3000bde113","spanId":"0bffe8e992ea29d2","parentSpanId":"","name":"ingress","kind":2,"startTimeUnixNano":"1724247952510920000","endTimeUnixNano":"1724247952513516000","attributes":[{"key":"node_id","value":{"stringValue":""}},{"key":"zone","value":{"stringValue":""}},{"key":"guid:x-request-id","value":{"stringValue":"f8ca422f-01cf-9c18-8191-7be359a70ef0"}},{"key":"http.url","value":{"stringValue":"http://frontend-proxy:8080/_next/static/chunks/pages/product/%5BproductId%5D-e419d8e486a0719c.js"}},{"key":"http.method","value":{"stringValue":"GET"}},{"key":"downstream_cluster","value":{"stringValue":"-"}},{"key":"user_agent","value":{"stringValue":"Mozilla/5.0 (X11; Linux x86_64) AppleWebKit/537.36 (KHTML, like Gecko) HeadlessChrome/120.0.6099.28 Safari/537.36"}},{"key":"http.protocol","value":{"stringValue":"HTTP/1.1"}},{"key":"peer.address","value":{"stringValue":"172.18.0.24"}},{"key":"request_size","value":{"stringValue":"0"}},{"key":"response_size","value":{"stringValue":"2360"}},{"key":"component","value":{"stringValue":"proxy"}},{"key":"upstream_cluster","value":{"stringValue":"frontend"}},{"key":"upstream_cluster.name","value":{"stringValue":"frontend"}},{"key":"http.status_code","value":{"stringValue":"200"}},{"key":"response_flags","value":{"stringValue":"-"}}],"status":{}}]}]}]}